urdf_parser_py/__init__.py
urdf_parser_py/display_urdf.py
urdf_parser_py/sdf.py
urdf_parser_py/urdf.py
urdf_parser_py/xml_reflection/__init__.py
urdf_parser_py/xml_reflection/basics.py
urdf_parser_py/xml_reflection/core.py
urdfdom_py-1.2.1.post1.data/data/share/ament_index/resource_index/packages/urdfdom_py
urdfdom_py-1.2.1.post1.data/data/share/urdfdom_py/package.xml
urdfdom_py-1.2.1.post1.dist-info/licenses/LICENSE
urdfdom_py-1.2.1.post1.dist-info/METADATA
urdfdom_py-1.2.1.post1.dist-info/WHEEL
urdfdom_py-1.2.1.post1.dist-info/entry_points.txt
urdfdom_py-1.2.1.post1.dist-info/top_level.txt
urdfdom_py-1.2.1.post1.dist-info/zip-safe
urdfdom_py-1.2.1.post1.dist-info/RECORD
